tripadvisor/__init__.py
tripadvisor/__main__.py
tripadvisor/cli.py
tripadvisor/debug.py
tripadvisor/loader.py
rgmining_tripadvisor_dataset-0.6.2.dist-info/COPYING
rgmining_tripadvisor_dataset-0.6.2.dist-info/METADATA
rgmining_tripadvisor_dataset-0.6.2.dist-info/WHEEL
rgmining_tripadvisor_dataset-0.6.2.dist-info/RECORD
