Metadata-Version: 2.3
Name: rgmining-tripadvisor-dataset
Version: 0.6.2
Summary: Trip Advisor dataset for Review Graph Mining Project
License: GPL-3.0-only
Keywords: dataset,mining,review
Author: Junpei Kawamoto
Author-email: kawamoto.junpei@gmail.com
Requires-Python: >=3.11
Classifier: Development Status :: 4 - Beta
Classifier: Intended Audience :: Science/Research
Classifier: License :: OSI Approved :: GNU General Public License v3 (GPLv3)
Classifier: Natural Language :: English
Classifier: Programming Language :: Python
Classifier: Programming Language :: Python :: 3 :: Only
Classifier: Programming Language :: Python :: 3.11
Classifier: Programming Language :: Python :: 3.12
Classifier: Programming Language :: Python :: 3.13
Classifier: Topic :: Scientific/Engineering :: Information Analysis
Classifier: Topic :: Software Development :: Libraries
Provides-Extra: cli
Requires-Dist: click (>=8) ; extra == "cli"
Requires-Dist: platformdirs (>=4.3.6,<5)
Requires-Dist: requests (>=2.32.3,<3)
Requires-Dist: rgmining-fraud-eagle (>=0.10.5) ; extra == "cli"
Requires-Dist: rgmining-fraudar (>=0.7.5) ; extra == "cli"
Requires-Dist: rgmining-rsd (>=0.3.5) ; extra == "cli"
Requires-Dist: tqdm (>=4.67.1,<5)
Project-URL: Documentation, https://rgmining.github.io/tripadvisor/
Project-URL: Homepage, https://rgmining.github.io/tripadvisor/
Project-URL: Repository, https://github.com/rgmining/tripadvisor
